indexify_langchain/__init__.py
indexify_langchain/retriever.py
indexify_langchain-0.0.36.dist-info/METADATA
indexify_langchain-0.0.36.dist-info/WHEEL
indexify_langchain-0.0.36.dist-info/RECORD
